<?xml version="1.0" ?><!DOCTYPE PubmedArticleSet PUBLIC "-//NLM//DTD PubMedArticle, 1st June 2018//EN" "https://dtd.nlm.nih.gov/ncbi/pubmed/out/pubmed_180601.dtd"><PubmedArticleSet><PubmedArticle>    <MedlineCitation Status="MEDLINE" Owner="NLM">        <PMID Version="1">30075530</PMID>        <DateCompleted>            <Year>2018</Year>            <Month>08</Month>            <Day>27</Day>        </DateCompleted>        <DateRevised>            <Year>2018</Year>            <Month>08</Month>            <Day>27</Day>        </DateRevised>        <Article PubModel="Print">            <Journal>                <ISSN IssnType="Electronic">1536-5964</ISSN>                <JournalIssue CitedMedium="Internet">                    <Volume>97</Volume>                    <Issue>31</Issue>                    <PubDate>                        <Year>2018</Year>                        <Month>Aug</Month>                    </PubDate>                </JournalIssue>                <Title>Medicine</Title>                <ISOAbbreviation>Medicine (Baltimore)</ISOAbbreviation>            </Journal>            <ArticleTitle>Chinese herbal products and the reduction of risk of breast cancer among females with type 2 diabetes in Taiwan: A case-control study.</ArticleTitle>            <Pagination>                <MedlinePgn>e11600</MedlinePgn>            </Pagination>            <ELocationID EIdType="doi" ValidYN="Y">10.1097/MD.0000000000011600</ELocationID>            <Abstract>                <AbstractText>Women with type 2 diabetes have a higher risk of developing breast cancer. In Taiwan, traditional Chinese medicine is widely used to treat diabetes; however, its precise influence has not been empirically tested.The objective of the case-control study is to estimate the effect on the risk of breast cancer of using traditional Chinese medicine for women with type 2 diabetes.More than 80% of women with type 2 diabetes have used traditional Chinese medicine. The most commonly prescribed drug was metformin and the herbal formulas were the Di Huang Wan series, including Liu Wei Di Huang Wan, Qi Ju Di Huang Wan, and Zhi Bai Di Huang Wan, followed by Bai Hu Jia Ren Shen Tang and Yu Quan Wan. For the effect of metformin, women who used traditional Chinese medicine including Di Huang series have a lower risk of breast cancer HR: 0.35 (95%CI: 0.23-0.51) in women younger than 55 and HR: 0.54 (95%CI: 0.37-0.79) in women older than 55.The protective effect of the Di Huang Wan series may be due to the synergetic effect of reducing blood glucose or increasing insulin sensitivity and delaying the insulin resistance of cells. The relationship between the Di Huang Wan series and breast cancer of women with type 2 diabetes requires further investigation.</AbstractText>            </Abstract>            <AuthorList CompleteYN="Y">                <Author ValidYN="Y">                    <LastName>Wu</LastName>                    <ForeName>Chien-Tung</ForeName>                    <Initials>CT</Initials>                    <AffiliationInfo>                        <Affiliation>Institute of Traditional Medicine, School of Medicine, National Yang-Ming University.</Affiliation>                    </AffiliationInfo>                    <AffiliationInfo>                        <Affiliation>Department of Chinese Medicine, Taipei City Hospital, Taipei.</Affiliation>                    </AffiliationInfo>                </Author>                <Author ValidYN="Y">                    <LastName>Tsai</LastName>                    <ForeName>Yueh-Ting</ForeName>                    <Initials>YT</Initials>                    <AffiliationInfo>                        <Affiliation>School of Chinese Medicine.</Affiliation>                    </AffiliationInfo>                    <AffiliationInfo>                        <Affiliation>Department of Chinese Medicine, China Medical University Hospital, Taichung, Taiwan.</Affiliation>                    </AffiliationInfo>                </Author>                <Author ValidYN="Y">                    <LastName>Lin</LastName>                    <ForeName>Jaung-Geng</ForeName>                    <Initials>JG</Initials>                    <AffiliationInfo>                        <Affiliation>School of Chinese Medicine.</Affiliation>                    </AffiliationInfo>                </Author>                <Author ValidYN="Y">                    <LastName>Fu</LastName>                    <ForeName>Shu-Ling</ForeName>                    <Initials>SL</Initials>                    <AffiliationInfo>                        <Affiliation>Institute of Traditional Medicine, School of Medicine, National Yang-Ming University.</Affiliation>                    </AffiliationInfo>                </Author>                <Author ValidYN="Y">                    <LastName>Lai</LastName>                    <ForeName>Jung-Nien</ForeName>                    <Initials>JN</Initials>                    <AffiliationInfo>                        <Affiliation>School of Chinese Medicine.</Affiliation>                    </AffiliationInfo>                    <AffiliationInfo>                        <Affiliation>Graduate Institute of Integrated Medicine.</Affiliation>                    </AffiliationInfo>                    <AffiliationInfo>                        <Affiliation>Department of Chinese Medicine, China Medical University Hospital, Taichung, Taiwan.</Affiliation>                    </AffiliationInfo>                </Author>            </AuthorList>            <Language>eng</Language>            <PublicationTypeList>                <PublicationType UI="D016428">Journal Article</PublicationType>                <PublicationType UI="D064888">Observational Study</PublicationType>            </PublicationTypeList>        </Article>        <MedlineJournalInfo>            <Country>United States</Country>            <MedlineTA>Medicine (Baltimore)</MedlineTA>            <NlmUniqueID>2985248R</NlmUniqueID>            <ISSNLinking>0025-7974</ISSNLinking>        </MedlineJournalInfo>        <ChemicalList>            <Chemical>                <RegistryNumber>0</RegistryNumber>                <NameOfSubstance UI="D004365">Drugs, Chinese Herbal</NameOfSubstance>            </Chemical>            <Chemical>                <RegistryNumber>0</RegistryNumber>                <NameOfSubstance UI="D007004">Hypoglycemic Agents</NameOfSubstance>            </Chemical>            <Chemical>                <RegistryNumber>9100L32L2N</RegistryNumber>                <NameOfSubstance UI="D008687">Metformin</NameOfSubstance>            </Chemical>        </ChemicalList>        <CitationSubset>AIM</CitationSubset>        <CitationSubset>IM</CitationSubset>        <CommentsCorrectionsList>            <CommentsCorrections RefType="Cites">                <RefSource>Genes Dis. 2015 Mar 1;2(1):13-25</RefSource>                <PMID Version="1">25984556</PMID>            </CommentsCorrections>            <CommentsCorrections RefType="Cites">                <RefSource>BMJ. 2015 Jan 02;350:g7607</RefSource>                <PMID Version="1">25555821</PMID>            </CommentsCorrections>            <CommentsCorrections RefType="Cites">                <RefSource>J Clin Oncol. 2012 Aug 10;30(23):2844-52</RefSource>                <PMID Version="1">22689798</PMID>            </CommentsCorrections>            <CommentsCorrections RefType="Cites">                <RefSource>Breast Cancer Res. 2009;11(5):R76</RefSource>                <PMID Version="1">19843326</PMID>            </CommentsCorrections>            <CommentsCorrections RefType="Cites">                <RefSource>J Clin Oncol. 2002 Jan 1;20(1):42-51</RefSource>                <PMID Version="1">11773152</PMID>            </CommentsCorrections>            <CommentsCorrections RefType="Cites">                <RefSource>PLoS One. 2015 Aug 20;10(8):e0136250</RefSource>                <PMID Version="1">26291325</PMID>            </CommentsCorrections>            <CommentsCorrections RefType="Cites">                <RefSource>PLoS One. 2011;6(10):e25183</RefSource>                <PMID Version="1">21998640</PMID>            </CommentsCorrections>            <CommentsCorrections RefType="Cites">                <RefSource>Breast Cancer Res. 2013 Jun 18;15(3):R46</RefSource>                <PMID Version="1">23777922</PMID>            </CommentsCorrections>            <CommentsCorrections RefType="Cites">                <RefSource>Biomed Res Int. 2015;2015:548436</RefSource>                <PMID Version="1">25866793</PMID>            </CommentsCorrections>            <CommentsCorrections RefType="Cites">                <RefSource>Diabetes Care. 2003 Jun;26(6):1752-8</RefSource>                <PMID Version="1">12766105</PMID>            </CommentsCorrections>            <CommentsCorrections RefType="Cites">                <RefSource>Am J Clin Nutr. 2007 Sep;86(3):s823-35</RefSource>                <PMID Version="1">18265476</PMID>            </CommentsCorrections>            <CommentsCorrections RefType="Cites">                <RefSource>BMC Public Health. 2013 Apr 09;13:318</RefSource>                <PMID Version="1">23570503</PMID>            </CommentsCorrections>            <CommentsCorrections RefType="Cites">                <RefSource>Evid Based Complement Alternat Med. 2013;2013:201329</RefSource>                <PMID Version="1">23843864</PMID>            </CommentsCorrections>            <CommentsCorrections RefType="Cites">                <RefSource>J Ethnopharmacol. 2014 Oct 28;156:358-64</RefSource>                <PMID Version="1">25178949</PMID>            </CommentsCorrections>            <CommentsCorrections RefType="Cites">                <RefSource>Ann Transl Med. 2014 Jun;2(6):57</RefSource>                <PMID Version="1">25333032</PMID>            </CommentsCorrections>            <CommentsCorrections RefType="Cites">                <RefSource>JAMA. 1999 Jun 2;281(21):2005-12</RefSource>                <PMID Version="1">10359389</PMID>            </CommentsCorrections>            <CommentsCorrections RefType="Cites">                <RefSource>Breast Cancer Res. 2015 Jun 26;17:88</RefSource>                <PMID Version="1">26111812</PMID>            </CommentsCorrections>            <CommentsCorrections RefType="Cites">                <RefSource>Diabetes Care. 2010 Jul;33(7):1674-85</RefSource>                <PMID Version="1">20587728</PMID>            </CommentsCorrections>        </CommentsCorrectionsList>        <MeshHeadingList>            <MeshHeading>                <DescriptorName UI="D000328" MajorTopicYN="N">Adult</DescriptorName>            </MeshHeading>            <MeshHeading>                <DescriptorName UI="D000368" MajorTopicYN="N">Aged</DescriptorName>            </MeshHeading>            <MeshHeading>                <DescriptorName UI="D001943" MajorTopicYN="N">Breast Neoplasms</DescriptorName>                <QualifierName UI="Q000453" MajorTopicYN="N">epidemiology</QualifierName>                <QualifierName UI="Q000517" MajorTopicYN="Y">prevention &amp; control</QualifierName>            </MeshHeading>            <MeshHeading>                <DescriptorName UI="D016022" MajorTopicYN="N">Case-Control Studies</DescriptorName>            </MeshHeading>            <MeshHeading>                <DescriptorName UI="D003924" MajorTopicYN="N">Diabetes Mellitus, Type 2</DescriptorName>                <QualifierName UI="Q000188" MajorTopicYN="Y">drug therapy</QualifierName>                <QualifierName UI="Q000453" MajorTopicYN="N">epidemiology</QualifierName>            </MeshHeading>            <MeshHeading>                <DescriptorName UI="D004359" MajorTopicYN="N">Drug Therapy, Combination</DescriptorName>            </MeshHeading>            <MeshHeading>                <DescriptorName UI="D004363" MajorTopicYN="N">Drug Utilization</DescriptorName>            </MeshHeading>            <MeshHeading>                <DescriptorName UI="D004365" MajorTopicYN="N">Drugs, Chinese Herbal</DescriptorName>                <QualifierName UI="Q000008" MajorTopicYN="N">administration &amp; dosage</QualifierName>                <QualifierName UI="Q000627" MajorTopicYN="Y">therapeutic use</QualifierName>            </MeshHeading>            <MeshHeading>                <DescriptorName UI="D005260" MajorTopicYN="N">Female</DescriptorName>            </MeshHeading>            <MeshHeading>                <DescriptorName UI="D006801" MajorTopicYN="N">Humans</DescriptorName>            </MeshHeading>            <MeshHeading>                <DescriptorName UI="D007004" MajorTopicYN="N">Hypoglycemic Agents</DescriptorName>                <QualifierName UI="Q000008" MajorTopicYN="N">administration &amp; dosage</QualifierName>                <QualifierName UI="Q000627" MajorTopicYN="Y">therapeutic use</QualifierName>            </MeshHeading>            <MeshHeading>                <DescriptorName UI="D008687" MajorTopicYN="N">Metformin</DescriptorName>                <QualifierName UI="Q000008" MajorTopicYN="N">administration &amp; dosage</QualifierName>                <QualifierName UI="Q000627" MajorTopicYN="Y">therapeutic use</QualifierName>            </MeshHeading>            <MeshHeading>                <DescriptorName UI="D008875" MajorTopicYN="N">Middle Aged</DescriptorName>            </MeshHeading>            <MeshHeading>                <DescriptorName UI="D016016" MajorTopicYN="N">Proportional Hazards Models</DescriptorName>            </MeshHeading>            <MeshHeading>                <DescriptorName UI="D013624" MajorTopicYN="N">Taiwan</DescriptorName>                <QualifierName UI="Q000453" MajorTopicYN="N">epidemiology</QualifierName>            </MeshHeading>            <MeshHeading>                <DescriptorName UI="D055815" MajorTopicYN="N">Young Adult</DescriptorName>            </MeshHeading>        </MeshHeadingList>    </MedlineCitation>    <PubmedData>        <History>            <PubMedPubDate PubStatus="entrez">                <Year>2018</Year>                <Month>8</Month>                <Day>5</Day>                <Hour>6</Hour>                <Minute>0</Minute>            </PubMedPubDate>            <PubMedPubDate PubStatus="pubmed">                <Year>2018</Year>                <Month>8</Month>                <Day>5</Day>                <Hour>6</Hour>                <Minute>0</Minute>            </PubMedPubDate>            <PubMedPubDate PubStatus="medline">                <Year>2018</Year>                <Month>8</Month>                <Day>28</Day>                <Hour>6</Hour>                <Minute>0</Minute>            </PubMedPubDate>        </History>        <PublicationStatus>ppublish</PublicationStatus>        <ArticleIdList>            <ArticleId IdType="pubmed">30075530</ArticleId>            <ArticleId IdType="doi">10.1097/MD.0000000000011600</ArticleId>            <ArticleId IdType="pii">00005792-201808030-00040</ArticleId>            <ArticleId IdType="pmc">PMC6081140</ArticleId>        </ArticleIdList>    </PubmedData></PubmedArticle></PubmedArticleSet>