<?xml version="1.0" ?><!DOCTYPE PubmedArticleSet PUBLIC "-//NLM//DTD PubMedArticle, 1st June 2018//EN" "https://dtd.nlm.nih.gov/ncbi/pubmed/out/pubmed_180601.dtd"><PubmedArticleSet><PubmedArticle>    <MedlineCitation Status="In-Process" Owner="NLM">        <PMID Version="1">30139233</PMID>        <DateRevised>            <Year>2018</Year>            <Month>10</Month>            <Day>16</Day>        </DateRevised>        <Article PubModel="Electronic">            <Journal>                <ISSN IssnType="Electronic">2476-762X</ISSN>                <JournalIssue CitedMedium="Internet">                    <Volume>19</Volume>                    <Issue>8</Issue>                    <PubDate>                        <Year>2018</Year>                        <Month>Aug</Month>                        <Day>24</Day>                    </PubDate>                </JournalIssue>                <Title>Asian Pacific journal of cancer prevention : APJCP</Title>                <ISOAbbreviation>Asian Pac. J. Cancer Prev.</ISOAbbreviation>            </Journal>            <ArticleTitle>Perceived Importance of Information Needs on Breast Cancer among Adults: a Population-Based Survey in the District of Colombo, Sri Lanka</ArticleTitle>            <Pagination>                <MedlinePgn>2247-2253</MedlinePgn>            </Pagination>            <Abstract>                <AbstractText>Background: Information needs of Breast Cancer (BC) and its perceived importance has not been adequatelyassessed in Sri Lanka. The present study aimed to assess cognitive information needs of BC among the adults. Methods:A household survey was conducted among a representative sample (n=1500) of over 18 years of age resident in thedistrict of Colombo not having BC patients in the families. A validated interviewer-administered questionnaire collectedinformation on general and cognitive information needs. Exploratory factor analysis assessed whether any of theaspects of informational needs are redundant and to group the needs. Results: Mean age of the participants was 37.21(SD = ±9.7) years. Proportion of females was 51.7%, 82.9% were married and 44.1% had been educated up to GeneralCertificate of Education (GCE) Ordinary Level. Exploratory factor analysis revealed all items of the questionnaire toform two groups that were named as “Factual information on BC prevention and early detection (screening and earlydiagnosis)” and “Factual information on BC diagnosis and treatment”. Results indicated that both groups of informationneeds were considered as highly important and the group “Factual information on BC diagnosis and treatment” (meanscore 4.20 ± 0.75) was perceived as more important than the other group. The perceived importance of informationneeds was shown to be significantly different based on the sex of the adults, marital status, level of education andthe employment status of the participants. Conclusion: This study demonstrates that cognitive information needs onBC are viewed as highly important by the general public. The study identified specific informational needs that areperceived as more important and some socio-demographic characteristics that are associated with higher perceivedneeds. The study recommends taking into account the findings of the study in designing the content and target groupsfor education on BC.</AbstractText>                <CopyrightInformation>Creative Commons Attribution License</CopyrightInformation>            </Abstract>            <AuthorList CompleteYN="Y">                <Author ValidYN="Y">                    <LastName>Kuruppu</LastName>                    <ForeName>D C</ForeName>                    <Initials>DC</Initials>                    <AffiliationInfo>                        <Affiliation>Medical Library, Faculty of Medicine, University of Colombo, Sri Lanka. Email: kuruppudc@gmail.com</Affiliation>                    </AffiliationInfo>                </Author>                <Author ValidYN="Y">                    <LastName>Wijeyaratne</LastName>                    <ForeName>C N</ForeName>                    <Initials>CN</Initials>                </Author>                <Author ValidYN="Y">                    <LastName>Gunawardena</LastName>                    <ForeName>Nalika</ForeName>                    <Initials>N</Initials>                </Author>                <Author ValidYN="Y">                    <LastName>Amarasinghe</LastName>                    <ForeName>I</ForeName>                    <Initials>I</Initials>                </Author>            </AuthorList>            <Language>eng</Language>            <PublicationTypeList>                <PublicationType UI="D016428">Journal Article</PublicationType>            </PublicationTypeList>            <ArticleDate DateType="Electronic">                <Year>2018</Year>                <Month>08</Month>                <Day>24</Day>            </ArticleDate>        </Article>        <MedlineJournalInfo>            <Country>Thailand</Country>            <MedlineTA>Asian Pac J Cancer Prev</MedlineTA>            <NlmUniqueID>101130625</NlmUniqueID>            <ISSNLinking>1513-7368</ISSNLinking>        </MedlineJournalInfo>        <CommentsCorrectionsList>            <CommentsCorrections RefType="Cites">                <RefSource>Health Soc Care Community. 2011 Nov;19(6):626-35</RefSource>                <PMID Version="1">21595770</PMID>            </CommentsCorrections>            <CommentsCorrections RefType="Cites">                <RefSource>Fam Cancer. 2003;2(2):119-21</RefSource>                <PMID Version="1">14649669</PMID>            </CommentsCorrections>            <CommentsCorrections RefType="Cites">                <RefSource>J Adv Nurs. 1997 Jun;25(6):1175-83</RefSource>                <PMID Version="1">9181414</PMID>            </CommentsCorrections>            <CommentsCorrections RefType="Cites">                <RefSource>J Adv Nurs. 1996 Mar;23(3):487-95</RefSource>                <PMID Version="1">8655823</PMID>            </CommentsCorrections>            <CommentsCorrections RefType="Cites">                <RefSource>CA Cancer J Clin. 2005 Mar-Apr;55(2):74-108</RefSource>                <PMID Version="1">15761078</PMID>            </CommentsCorrections>            <CommentsCorrections RefType="Cites">                <RefSource>Oncol Nurs Forum. 1997 Apr;24(3):473-80</RefSource>                <PMID Version="1">9127360</PMID>            </CommentsCorrections>            <CommentsCorrections RefType="Cites">                <RefSource>Oncol Nurs Forum. 2002 Jul;29(6):E77-84</RefSource>                <PMID Version="1">12096298</PMID>            </CommentsCorrections>            <CommentsCorrections RefType="Cites">                <RefSource>World Health Stat Q. 1991;44(3):98-106</RefSource>                <PMID Version="1">1949887</PMID>            </CommentsCorrections>            <CommentsCorrections RefType="Cites">                <RefSource>Oncol Nurs Forum. 1998 Oct;25(9):1595-601</RefSource>                <PMID Version="1">9802055</PMID>            </CommentsCorrections>            <CommentsCorrections RefType="Cites">                <RefSource>Eur J Cancer Care (Engl). 2003 Mar;12(1):81-90</RefSource>                <PMID Version="1">12641560</PMID>            </CommentsCorrections>            <CommentsCorrections RefType="Cites">                <RefSource>Psychooncology. 2010 Apr;19(4):423-30</RefSource>                <PMID Version="1">19598293</PMID>            </CommentsCorrections>            <CommentsCorrections RefType="Cites">                <RefSource>J Adv Nurs. 1997 Jul;26(1):59-64</RefSource>                <PMID Version="1">9231278</PMID>            </CommentsCorrections>            <CommentsCorrections RefType="Cites">                <RefSource>Asia Pac Fam Med. 2008 Dec 20;7(1):6</RefSource>                <PMID Version="1">19099595</PMID>            </CommentsCorrections>            <CommentsCorrections RefType="Cites">                <RefSource>BMC Public Health. 2013 Dec 20;13:1209</RefSource>                <PMID Version="1">24359310</PMID>            </CommentsCorrections>            <CommentsCorrections RefType="Cites">                <RefSource>Asian Pac J Cancer Prev. 2013;14(12):7639-44</RefSource>                <PMID Version="1">24460346</PMID>            </CommentsCorrections>            <CommentsCorrections RefType="Cites">                <RefSource>JAMA. 1997 May 14;277(18):1485-92</RefSource>                <PMID Version="1">9145723</PMID>            </CommentsCorrections>        </CommentsCorrectionsList>        <KeywordList Owner="NOTNLM">            <Keyword MajorTopicYN="Y">Breast cancer</Keyword>            <Keyword MajorTopicYN="Y">breast self-examination</Keyword>            <Keyword MajorTopicYN="Y">early detection of cancer</Keyword>            <Keyword MajorTopicYN="Y">health education</Keyword>            <Keyword MajorTopicYN="Y">health literacy</Keyword>        </KeywordList>    </MedlineCitation>    <PubmedData>        <History>            <PubMedPubDate PubStatus="entrez">                <Year>2018</Year>                <Month>8</Month>                <Day>25</Day>                <Hour>6</Hour>                <Minute>0</Minute>            </PubMedPubDate>            <PubMedPubDate PubStatus="pubmed">                <Year>2018</Year>                <Month>8</Month>                <Day>25</Day>                <Hour>6</Hour>                <Minute>0</Minute>            </PubMedPubDate>            <PubMedPubDate PubStatus="medline">                <Year>2018</Year>                <Month>8</Month>                <Day>25</Day>                <Hour>6</Hour>                <Minute>0</Minute>            </PubMedPubDate>        </History>        <PublicationStatus>epublish</PublicationStatus>        <ArticleIdList>            <ArticleId IdType="pubmed">30139233</ArticleId>            <ArticleId IdType="doi">10.22034/APJCP.2018.19.8.2247</ArticleId>            <ArticleId IdType="pmc">PMC6171379</ArticleId>        </ArticleIdList>    </PubmedData></PubmedArticle></PubmedArticleSet>